cli.py
main.py
core/db.py
core/commands/delete.py
core/commands/get.py
core/commands/list.py
core/commands/store.py
core/commands/update.py
keybin-1.0.0.dist-info/LICENSE
keybin-1.0.0.dist-info/METADATA
keybin-1.0.0.dist-info/WHEEL
keybin-1.0.0.dist-info/top_level.txt
keybin-1.0.0.dist-info/RECORD
