Metadata-Version: 2.1
Name: keybin
Version: 1.0.0
Summary: keybin is a command-line interface tool built with python for secure management of API and secret keys using the Panega Vault service.
Author-email: Yeshwant Kuriyavar <yeshwa916@gmail.com>
Project-URL: Homepage, https://github.com/Yeva916/keybin
Project-URL: Issues, https://github.com/Yeva916/keybin/issues
Classifier: Programming Language :: Python :: 3
Classifier: License :: OSI Approved :: MIT License
Classifier: Operating System :: OS Independent
Requires-Python: >=3.8
License-File: LICENSE
Requires-Dist: certifi ==2024.7.4
Requires-Dist: charset-normalizer ==3.3.2
Requires-Dist: dnspython ==2.6.1
Requires-Dist: idna ==3.8
Requires-Dist: pangea ==0.1.0
Requires-Dist: pymongo ==4.8.0
Requires-Dist: pyperclip ==1.9.0
Requires-Dist: python-dotenv ==1.0.1
Requires-Dist: requests ==2.32.3
Requires-Dist: urllib3 ==2.2.2
